b_aws_websocket_api/__init__.py
b_aws_websocket_api/ws_api.py
b_aws_websocket_api/ws_deployment.py
b_aws_websocket_api/ws_function.py
b_aws_websocket_api/ws_integration.py
b_aws_websocket_api/ws_lambda_integration.py
b_aws_websocket_api/ws_route.py
b_aws_websocket_api/ws_stage.py
b_aws_websocket_api_test/tests/__init__.py
b_aws_websocket_api_test/tests/test_invoke_function.py
b_aws_websocket_api_test/tests/test_websocket_connection.py
b_aws_websocket_api-2.0.0.dist-info/LICENSE
b_aws_websocket_api-2.0.0.dist-info/METADATA
b_aws_websocket_api-2.0.0.dist-info/WHEEL
b_aws_websocket_api-2.0.0.dist-info/top_level.txt
b_aws_websocket_api-2.0.0.dist-info/RECORD
