Metadata-Version: 2.1
Name: b-aws-websocket-api
Version: 2.0.0
Summary: AWS CDK package that helps creating web socket APIs.
Home-page: https://github.com/Biomapas/B.AwsWebsocketApi.git
Author: Laimonas Sutkus
Author-email: laimonas.sutkus@biomapas.com
License: Apache License 2.0
Keywords: AWS CDK API WebSocket
Classifier: Programming Language :: Python :: 3
Classifier: Operating System :: OS Independent
License-File: LICENSE
Requires-Dist: aws-cdk-lib <3.0.0,>=2.0.0
Requires-Dist: aws-cdk-constructs <3.0.0,>=2.0.0
Requires-Dist: b-stage-deployment <2.0.0,>=1.0.0
Requires-Dist: websockets <12.0.0,>=11.0.0
Requires-Dist: pytest <7.0.0,>=6.0.2
Requires-Dist: pytest-cov <3.0.0,>=2.10.1
Requires-Dist: pytest-timeout <1.5.0,>=1.3.4
